big_query_kusto_client/__init__.py
big_query_kusto_client/bigquerykustoclient.py
big_query_kusto_client-0.4.0.dist-info/METADATA
big_query_kusto_client-0.4.0.dist-info/WHEEL
big_query_kusto_client-0.4.0.dist-info/RECORD
