Metadata-Version: 2.3
Name: big-query-kusto-client
Version: 0.4.0
Summary: Wrapper around azure-kusto client to facilitate bringing BIG query results while avoiding hitting the limits
License: Apache-2.0
Author: JJ Triff
Author-email: jjtriff@gmail.com
Requires-Python: >=3.9,<4.0
Classifier: License :: OSI Approved :: Apache Software License
Classifier: Programming Language :: Python :: 3
Classifier: Programming Language :: Python :: 3.9
Classifier: Programming Language :: Python :: 3.10
Classifier: Programming Language :: Python :: 3.11
Classifier: Programming Language :: Python :: 3.12
Classifier: Programming Language :: Python :: 3.13
Requires-Dist: azure-kusto-data (>=4.2.0,<5.0.0)
Requires-Dist: pandas (>=2.2.2,<3.0.0)
Requires-Dist: tenacity (>=9.1.2,<10.0.0)
Project-URL: Homepage, https://github.com/jjtriff/big-query-kusto-client
